indexed_dict/__init__.py
indexed_dict/_node.py
indexed_dict/_types.py
indexed_dict/_views.py
indexed_dict/indexed_dict.py
indexed_dict/py.typed
indexed_dict-0.3.1.dist-info/METADATA
indexed_dict-0.3.1.dist-info/WHEEL
indexed_dict-0.3.1.dist-info/licenses/LICENSE.md
indexed_dict-0.3.1.dist-info/RECORD
