Metadata-Version: 2.4
Name: indexed-dict
Version: 0.3.1
Summary: A dictionary that preserves insertion order and allows index-based operations.
Author-email: Ashlynn Antrobus <ashlynn@prosepal.io>
License: MIT
License-File: LICENSE.md
Classifier: Intended Audience :: Developers
Classifier: License :: OSI Approved :: MIT License
Classifier: Operating System :: OS Independent
Classifier: Programming Language :: Python :: 3
Classifier: Programming Language :: Python :: 3 :: Only
Classifier: Programming Language :: Python :: 3.10
Classifier: Programming Language :: Python :: 3.11
Classifier: Programming Language :: Python :: 3.12
Classifier: Programming Language :: Python :: 3.13
Classifier: Topic :: Software Development :: Libraries :: Python Modules
Classifier: Typing :: Typed
Requires-Python: >=3.10
